zipcode_to_map/__init__.py
zipcode_to_map/example_usage.py
zipcode_to_map/setup.py
zipcode_to_map/zipcode_to_map.py
bharathjinka09-1.0.dist-info/METADATA
bharathjinka09-1.0.dist-info/WHEEL
bharathjinka09-1.0.dist-info/top_level.txt
bharathjinka09-1.0.dist-info/RECORD
