Metadata-Version: 2.1
Name: bharathjinka09
Version: 1.0
Summary: Provide a Country code and postal code.It will generate a map in a html file based on these details.Used pgeocode and folium packages.
Home-page: https://github.com/bharathjinka09/zipcode_to_map/
Author: JINKA RANGA BHARATH
Author-email: bharathjinka09@gmail.com
License: UNKNOWN
Platform: UNKNOWN
Classifier: Programming Language :: Python :: 3
Classifier: License :: OSI Approved :: MIT License
Classifier: Operating System :: OS Independent
Requires-Python: >=3.6
